dhmsaiadtrain/DHMS_AI_Alert_Model.py
dhmsaiadtrain/GPU_manager.py
dhmsaiadtrain/__init__.py
dhmsaiadtrain/device_info_reader.py
dhmsaiadtrain/sampling_preprocess.py
dhmsaiadtrain/train_manager.py
dhmsaiadtrain-0.1.dist-info/LICENSE
dhmsaiadtrain-0.1.dist-info/METADATA
dhmsaiadtrain-0.1.dist-info/WHEEL
dhmsaiadtrain-0.1.dist-info/top_level.txt
dhmsaiadtrain-0.1.dist-info/RECORD
