Metadata-Version: 2.1
Name: dhmsaiadtrain
Version: 0.1
Summary: AI Training Script Owned by Suzhou DHMS
Home-page: https://gitlab.dhms.net/aidiagnosis/ai_alert_training
Author: Daijie Bao
Author-email: daijiebao0617@outlook.com
License: UNKNOWN
Platform: UNKNOWN
Requires-Python: >=3.8
License-File: LICENSE
Requires-Dist: numpy (>=1.23.2)
Requires-Dist: tensorflow (>=2.12.0)
Requires-Dist: keras (>=2.12.0)
Requires-Dist: scikit-learn (>=1.2.1)
Requires-Dist: pandas (>=1.5.3)
Requires-Dist: matplotlib (>=3.7.1)
